inneed_utility_service/__init__.py
inneed_utility_service/decorators/__init__.py
inneed_utility_service/decorators/decorators.py
inneed_utility_service/dynamodb_utility/__init__.py
inneed_utility_service/dynamodb_utility/dynamodb_client.py
inneed_utility_service/enums/__init__.py
inneed_utility_service/enums/enums.py
inneed_utility_service/error_utility/__init__.py
inneed_utility_service/error_utility/error_handler.py
inneed_utility_service/response_utility/__init__.py
inneed_utility_service/response_utility/response_helpers.py
inneed_utility_service/s3_utility/__init__.py
inneed_utility_service/s3_utility/s3_client.py
inneed_utility_service-0.1.2.dist-info/LICENSE
inneed_utility_service-0.1.2.dist-info/METADATA
inneed_utility_service-0.1.2.dist-info/WHEEL
inneed_utility_service-0.1.2.dist-info/top_level.txt
inneed_utility_service-0.1.2.dist-info/RECORD
