Metadata-Version: 2.2
Name: inneed-utility-service
Version: 0.1.2
Summary: A multi-service AWS utilities library with FastAPI helpers, enums, and additional utility functions.
Home-page: https://github.com/MuhibNayem/inneed_utility_service.git
Author: A K M Muhibullah Nayem
Author-email: A K M Muhibullah Nayem <muhibullah@inneed.cloud>
Maintainer-email: A K M Muhibullah Nayem <muhibullah@inneed.cloud>
License: MIT License
Keywords: fastapi,aws,utilities,enums,responses
Classifier: Programming Language :: Python :: 3
Classifier: License :: OSI Approved :: MIT License
Classifier: Operating System :: OS Independent
Classifier: Framework :: FastAPI
Requires-Python: >=3.7
License-File: LICENSE
Requires-Dist: fastapi
Requires-Dist: uvicorn
Requires-Dist: boto3
Requires-Dist: aioboto3
Provides-Extra: test
Requires-Dist: pytest; extra == "test"
Requires-Dist: httpx; extra == "test"
Requires-Dist: moto; extra == "test"
